MANIFEST.in
README.md
setup.cfg
setup.py
cpselect/__init__.py
cpselect/cpselect.py
cpselect.egg-info/PKG-INFO
cpselect.egg-info/SOURCES.txt
cpselect.egg-info/dependency_links.txt
cpselect.egg-info/requires.txt
cpselect.egg-info/top_level.txt
cpselect/img/backforwardbutton.png
cpselect/img/cpselect32.ico
cpselect/img/homebutton.png
cpselect/img/navbuttons.PNG
cpselect/img/panzoombutton.png
cpselect/img/zoomboxbutton.png
cpselect/test/__init__.py