Metadata-Version: 2.1
Name: cpselect
Version: 1.0.3
Summary: Does what cpselect does in MATLAB.
Home-page: https://github.com/adal02/phg-cpselect
Author: adal02
Author-email: adal02.py@gmail.com
License: UNKNOWN
Platform: UNKNOWN
Classifier: Programming Language :: Python :: 3.6
Classifier: License :: OSI Approved :: MIT License
Classifier: Development Status :: 4 - Beta
